README.rst
setup.cfg
setup.py
munexus.egg-info/PKG-INFO
munexus.egg-info/SOURCES.txt
munexus.egg-info/dependency_links.txt
munexus.egg-info/top_level.txt
munxs/__init__.py
munxs/napi.py
munxs/tree.py
munxs/unit.py