Metadata-Version: 1.1
Name: munexus
Version: 0.1
Summary: A Python hack for the nexus python bindings, that reads ISIS muon data.
Home-page: https://github.com/RDeRenzi/munexus
Author: Roberto De Renzi, (Paul Kienzle)
Author-email: roberto.derenzi@unipr.it
License: LGPLv2
Platform: UNKNOWN
Classifier: Programming Language :: Python :: 3
